LICENSE
MANIFEST.in
README.rst
setup.py
Djaq.egg-info/PKG-INFO
Djaq.egg-info/SOURCES.txt
Djaq.egg-info/dependency_links.txt
Djaq.egg-info/top_level.txt
djaq/__init__.py
djaq/app_utils.py
djaq/conditions.py
djaq/exceptions.py
djaq/functions.py
djaq/result.py
djaq/djaq_api/__init__.py
djaq/djaq_api/admin.py
djaq/djaq_api/apps.py
djaq/djaq_api/models.py
djaq/djaq_api/tests.py
djaq/djaq_api/urls.py
djaq/djaq_api/views.py
djaq/djaq_api/migrations/__init__.py
djaq/djaq_ui/__init__.py
djaq/djaq_ui/admin.py
djaq/djaq_ui/apps.py
djaq/djaq_ui/models.py
djaq/djaq_ui/tests.py
djaq/djaq_ui/urls.py
djaq/djaq_ui/views.py
djaq/djaq_ui/management/__init__.py
djaq/djaq_ui/management/commands/__init__.py
djaq/djaq_ui/management/commands/build_data.py
djaq/djaq_ui/management/commands/djaq.py
djaq/djaq_ui/management/commands/run.py
djaq/djaq_ui/migrations/__init__.py
djaq/djaq_ui/templates/base_query.html
djaq/djaq_ui/templates/query.html
djaq/query/__init__.py