Metadata-Version: 2.1
Name: Djaq
Version: 1.0.8
Summary: A string-based Django query language
Home-page: https://github.com/paul-wolf/djaq
Author: Paul Wolf
Author-email: paul.wolf@yewleaf.com
License: MIT
Classifier: Development Status :: 5 - Production/Stable
Classifier: Intended Audience :: Developers
Classifier: License :: OSI Approved :: MIT License
Classifier: Programming Language :: Python
Classifier: Programming Language :: Python :: 3.7
Classifier: Programming Language :: Python :: 3.8
Classifier: Programming Language :: Python :: 3.9
Classifier: Programming Language :: Python :: 3.10
Classifier: Framework :: Django
Classifier: Topic :: Software Development :: Libraries :: Python Modules
License-File: LICENSE
